[{"gender":"male","category":"Chemistry"},{"gender":"male","category":"Chemistry"},{"gender":"male","category":"Physiology or Medicine"},{"gender":"male","category":"Physics"},{"gender":"male","category":"Physics"},{"gender":"male","category":"Physiology or Medicine"},{"gender":"male","category":"Economics"},{"gender":"male","category":"Physics"},{"gender":"male","category":"Physiology or Medicine"},{"gender":"male","category":"Physiology or Medicine"},{"gender":"male","category":"Economics"},{"gender":"male","category":"Physics"},{"gender":"male","category":"Physics"},{"gender":"male","category":"Physics"},{"gender":"male","category":"Physics"},{"gender":"male","category":"Physics"},{"gender":"male","category":"Physiology or Medicine"},{"gender":"male","category":"Physiology or Medicine"},{"gender":"male","category":"Physics"},{"gender":"male","category":"Physics"},{"gender":"male","category":"Physiology or Medicine"},{"gender":"male","category":"Physiology or Medicine"},{"gender":"male","category":"Peace"},{"gender":"male","category":"Chemistry"},{"gender":"male","category":"Chemistry"},{"gender":"male","category":"Economics"},{"gender":"male","category":"Economics"},{"gender":"female","category":"Peace"},{"gender":"male","category":"Literature"},{"gender":"male","category":"Chemistry"},{"gender":"male","category":"Peace"},{"gender":"male","category":"Physics"},{"gender":"male","category":"Peace"},{"gender":"male","category":"Physics"},{"gender":"male","category":"Peace"},{"gender":"male","category":"Physics"},{"gender":"male","category":"Peace"},{"gender":"male","category":"Literature"},{"gender":"male","category":"Peace"},{"gender":"male","category":"Physics"},{"gender":"female","category":"Literature"},{"gender":"male","category":"Physics"},{"gender":"male","category":"Literature"},{"gender":"male","category":"Physics"},{"gender":"male","category":"Chemistry"},{"gender":"male","category":"Physiology or Medicine"},{"gender":"male","category":"Physiology or Medicine"},{"gender":"male","category":"Physics"},{"gender":"male","category":"Physiology or Medicine"},{"gender":"male","category":"Physiology or Medicine"},{"gender":"male","category":"Physiology or Medicine"},{"gender":"male","category":"Physiology or Medicine"},{"gender":"male","category":"Physiology or Medicine"},{"gender":"male","category":"Chemistry"},{"gender":"female","category":"Peace"},{"gender":"male","category":"Peace"},{"gender":"male","category":"Peace"},{"gender":"male","category":"Physics"},{"gender":"female","category":"Physiology or Medicine"},{"gender":"male","category":"Chemistry"},{"gender":"male","category":"Chemistry"},{"gender":"male","category":"Chemistry"},{"gender":"male","category":"Physiology or Medicine"},{"gender":"male","category":"Chemistry"},{"gender":"male","category":"Chemistry"},{"gender":"male","category":"Peace"},{"gender":"male","category":"Physiology or Medicine"},{"gender":"male","category":"Physiology or Medicine"},{"gender":"male","category":"Chemistry"},{"gender":"male","category":"Literature"},{"gender":"female","category":"Peace"},{"gender":"male","category":"Peace"},{"gender":"male","category":"Physics"},{"gender":"male","category":"Physiology or Medicine"},{"gender":"male","category":"Peace"},{"gender":"male","category":"Physiology or Medicine"},{"gender":"male","category":"Physics"},{"gender":"male","category":"Physics"},{"gender":"male","category":"Physics"},{"gender":"male","category":"Chemistry"},{"gender":"male","category":"Literature"},{"gender":"male","category":"Physics"},{"gender":"male","category":"Physics"},{"gender":"male","category":"Physics"},{"gender":"male","category":"Physiology or Medicine"},{"gender":"male","category":"Physiology or Medicine"},{"gender":"male","category":"Chemistry"},{"gender":"male","category":"Physics"},{"gender":"male","category":"Physiology or Medicine"},{"gender":"male","category":"Physiology or Medicine"},{"gender":"male","category":"Physiology or Medicine"},{"gender":"male","category":"Physiology or Medicine"},{"gender":"male","category":"Physiology or Medicine"},{"gender":"male","category":"Physiology or Medicine"},{"gender":"male","category":"Physiology or Medicine"},{"gender":"male","category":"Physics"},{"gender":"male","category":"Peace"},{"gender":"male","category":"Physiology or Medicine"},{"gender":"male","category":"Chemistry"},{"gender":"male","category":"Physics"},{"gender":"male","category":"Physiology or Medicine"},{"gender":"male","category":"Chemistry"},{"gender":"male","category":"Physics"},{"gender":"male","category":"Physics"},{"gender":"male","category":"Physics"},{"gender":"male","category":"Physiology or Medicine"},{"gender":"male","category":"Physics"},{"gender":"male","category":"Peace"},{"gender":"male","category":"Physics"},{"gender":"male","category":"Physiology or Medicine"},{"gender":"female","category":"Physics"},{"gender":"male","category":"Chemistry"},{"gender":"male","category":"Physiology or Medicine"},{"gender":"male","category":"Physiology or Medicine"},{"gender":"male","category":"Chemistry"},{"gender":"male","category":"Physics"},{"gender":"male","category":"Physics"},{"gender":"male","category":"Literature"},{"gender":"male","category":"Physiology or Medicine"},{"gender":"male","category":"Physiology or Medicine"},{"gender":"male","category":"Physiology or Medicine"},{"gender":"male","category":"Physics"},{"gender":"male","category":"Physiology or Medicine"},{"gender":"male","category":"Physiology or Medicine"},{"gender":"male","category":"Physiology or Medicine"},{"gender":"male","category":"Physiology or Medicine"},{"gender":"male","category":"Economics"},{"gender":"male","category":"Peace"},{"gender":"male","category":"Physiology or Medicine"},{"gender":"male","category":"Physics"},{"gender":"male","category":"Physiology or Medicine"},{"gender":"male","category":"Physics"},{"gender":"male","category":"Physiology or Medicine"},{"gender":"male","category":"Physiology or Medicine"},{"gender":"male","category":"Economics"},{"gender":"male","category":"Peace"},{"gender":"male","category":"Chemistry"},{"gender":"male","category":"Chemistry"},{"gender":"male","category":"Chemistry"},{"gender":"male","category":"Economics"},{"gender":"male","category":"Physiology or Medicine"},{"gender":"male","category":"Physics"},{"gender":"male","category":"Physiology or Medicine"},{"gender":"male","category":"Physiology or Medicine"},{"gender":"male","category":"Physiology or Medicine"},{"gender":"male","category":"Chemistry"},{"gender":"male","category":"Physics"},{"gender":"male","category":"Physics"},{"gender":"male","category":"Physics"},{"gender":"male","category":"Physiology or Medicine"},{"gender":"male","category":"Literature"},{"gender":"male","category":"Physics"},{"gender":"male","category":"Physics"},{"gender":"male","category":"Physiology or Medicine"},{"gender":"male","category":"Physiology or Medicine"},{"gender":"female","category":"Physiology or Medicine"},{"gender":"male","category":"Chemistry"},{"gender":"male","category":"Economics"},{"gender":"male","category":"Economics"},{"gender":"male","category":"Literature"},{"gender":"male","category":"Physics"},{"gender":"male","category":"Physics"},{"gender":"male","category":"Physiology or Medicine"},{"gender":"male","category":"Physiology or Medicine"},{"gender":"male","category":"Physics"},{"gender":"male","category":"Physics"},{"gender":"male","category":"Physiology or Medicine"},{"gender":"male","category":"Physiology or Medicine"},{"gender":"male","category":"Chemistry"},{"gender":"male","category":"Chemistry"},{"gender":"male","category":"Economics"},{"gender":"male","category":"Literature"},{"gender":"male","category":"Physics"},{"gender":"male","category":"Physics"},{"gender":"male","category":"Physiology or Medicine"},{"gender":"male","category":"Economics"},{"gender":"male","category":"Physics"},{"gender":"male","category":"Chemistry"},{"gender":"male","category":"Economics"},{"gender":"male","category":"Physics"},{"gender":"male","category":"Physics"},{"gender":"male","category":"Physiology or Medicine"},{"gender":"male","category":"Physiology or Medicine"},{"gender":"male","category":"Chemistry"},{"gender":"male","category":"Economics"},{"gender":"male","category":"Physics"},{"gender":"female","category":"Physiology or Medicine"},{"gender":"male","category":"Chemistry"},{"gender":"male","category":"Chemistry"},{"gender":"male","category":"Economics"},{"gender":"male","category":"Physiology or Medicine"},{"gender":"male","category":"Physiology or Medicine"},{"gender":"male","category":"Physiology or Medicine"},{"gender":"female","category":"Physiology or Medicine"},{"gender":"male","category":"Chemistry"},{"gender":"male","category":"Chemistry"},{"gender":"male","category":"Chemistry"},{"gender":"male","category":"Chemistry"},{"gender":"male","category":"Economics"},{"gender":"male","category":"Peace"},{"gender":"male","category":"Physics"},{"gender":"male","category":"Economics"},{"gender":"male","category":"Economics"},{"gender":"male","category":"Economics"},{"gender":"male","category":"Literature"},{"gender":"male","category":"Physics"},{"gender":"male","category":"Physics"},{"gender":"male","category":"Physics"},{"gender":"female","category":"Physiology or Medicine"},{"gender":"male","category":"Physiology or Medicine"},{"gender":"male","category":"Chemistry"},{"gender":"male","category":"Chemistry"},{"gender":"male","category":"Chemistry"},{"gender":"male","category":"Chemistry"},{"gender":"male","category":"Physics"},{"gender":"male","category":"Physics"},{"gender":"male","category":"Physiology or Medicine"},{"gender":"male","category":"Physiology or Medicine"},{"gender":"male","category":"Physiology or Medicine"},{"gender":"male","category":"Chemistry"},{"gender":"male","category":"Economics"},{"gender":"male","category":"Physiology or Medicine"},{"gender":"male","category":"Economics"},{"gender":"male","category":"Chemistry"},{"gender":"male","category":"Economics"},{"gender":"male","category":"Physiology or Medicine"},{"gender":"male","category":"Chemistry"},{"gender":"male","category":"Economics"},{"gender":"male","category":"Economics"},{"gender":"female","category":"Literature"},{"gender":"male","category":"Physics"},{"gender":"male","category":"Physics"},{"gender":"male","category":"Physiology or Medicine"},{"gender":"male","category":"Economics"},{"gender":"male","category":"Economics"},{"gender":"male","category":"Physics"},{"gender":"male","category":"Physics"},{"gender":"male","category":"Physiology or Medicine"},{"gender":"male","category":"Physiology or Medicine"},{"gender":"male","category":"Chemistry"},{"gender":"male","category":"Chemistry"},{"gender":"male","category":"Economics"},{"gender":"male","category":"Physics"},{"gender":"male","category":"Physics"},{"gender":"male","category":"Physiology or Medicine"},{"gender":"male","category":"Physiology or Medicine"},{"gender":"male","category":"Chemistry"},{"gender":"male","category":"Chemistry"},{"gender":"male","category":"Economics"},{"gender":"male","category":"Physics"},{"gender":"male","category":"Chemistry"},{"gender":"male","category":"Physiology or Medicine"},{"gender":"male","category":"Chemistry"},{"gender":"female","category":"Peace"},{"gender":"male","category":"Physics"},{"gender":"male","category":"Physics"},{"gender":"male","category":"Physiology or Medicine"},{"gender":"male","category":"Physics"},{"gender":"male","category":"Physics"},{"gender":"male","category":"Economics"},{"gender":"male","category":"Economics"},{"gender":"male","category":"Physics"},{"gender":"male","category":"Chemistry"},{"gender":"male","category":"Economics"},{"gender":"male","category":"Economics"},{"gender":"male","category":"Physics"},{"gender":"male","category":"Physiology or Medicine"},{"gender":"male","category":"Chemistry"},{"gender":"male","category":"Physics"},{"gender":"male","category":"Physics"},{"gender":"male","category":"Physiology or Medicine"},{"gender":"male","category":"Chemistry"},{"gender":"male","category":"Chemistry"},{"gender":"male","category":"Economics"},{"gender":"male","category":"Economics"},{"gender":"male","category":"Economics"},{"gender":"male","category":"Physics"},{"gender":"male","category":"Physics"},{"gender":"male","category":"Physiology or Medicine"},{"gender":"male","category":"Physiology or Medicine"},{"gender":"male","category":"Peace"},{"gender":"male","category":"Physics"},{"gender":"male","category":"Physiology or Medicine"},{"gender":"female","category":"Physiology or Medicine"},{"gender":"male","category":"Chemistry"},{"gender":"male","category":"Chemistry"},{"gender":"male","category":"Economics"},{"gender":"male","category":"Economics"},{"gender":"male","category":"Physics"},{"gender":"male","category":"Physiology or Medicine"},{"gender":"male","category":"Physiology or Medicine"},{"gender":"male","category":"Chemistry"},{"gender":"male","category":"Chemistry"},{"gender":"male","category":"Chemistry"},{"gender":"male","category":"Economics"},{"gender":"male","category":"Physics"},{"gender":"male","category":"Physics"},{"gender":"male","category":"Physics"},{"gender":"male","category":"Physiology or Medicine"},{"gender":"male","category":"Physics"},{"gender":"male","category":"Economics"},{"gender":"male","category":"Economics"},{"gender":"male","category":"Economics"},{"gender":"male","category":"Peace"},{"gender":"male","category":"Physiology or Medicine"},{"gender":"male","category":"Physiology or Medicine"},{"gender":"male","category":"Chemistry"},{"gender":"male","category":"Physics"},{"gender":"male","category":"Economics"},{"gender":"male","category":"Chemistry"},{"gender":"male","category":"Chemistry"},{"gender":"male","category":"Chemistry"},{"gender":"male","category":"Physics"},{"gender":"male","category":"Economics"},{"gender":"male","category":"Economics"},{"gender":"female","category":"Physiology or Medicine"},{"gender":"male","category":"Chemistry"},{"gender":"male","category":"Physics"},{"gender":"male","category":"Physics"},{"gender":"female","category":"Physiology or Medicine"},{"gender":"female","category":"Economics"},{"gender":"male","category":"Economics"},{"gender":"male","category":"Peace"},{"gender":"male","category":"Chemistry"},{"gender":"male","category":"Economics"},{"gender":"male","category":"Physics"},{"gender":"male","category":"Physics"},{"gender":"male","category":"Physics"},{"gender":"male","category":"Physiology or Medicine"},{"gender":"male","category":"Economics"},{"gender":"male","category":"Chemistry"},{"gender":"male","category":"Physiology or Medicine"},{"gender":"male","category":"Physiology or Medicine"},{"gender":"male","category":"Physiology or Medicine"},{"gender":"male","category":"Economics"},{"gender":"male","category":"Economics"},{"gender":"male","category":"Chemistry"},{"gender":"male","category":"Chemistry"},{"gender":"male","category":"Physics"},{"gender":"male","category":"Economics"},{"gender":"male","category":"Economics"},{"gender":"male","category":"Economics"},{"gender":"male","category":"Economics"},{"gender":"male","category":"Economics"},{"gender":"male","category":"Literature"},{"gender":"male","category":"Chemistry"},{"gender":"male","category":"Chemistry"},{"gender":"male","category":"Physiology or Medicine"},{"gender":"male","category":"Physiology or Medicine"},{"gender":"male","category":"Physiology or Medicine"},{"gender":"male","category":"Chemistry"},{"gender":"male","category":"Chemistry"},{"gender":"male","category":"Physics"},{"gender":"male","category":"Physiology or Medicine"},{"gender":"male","category":"Physiology or Medicine"},{"gender":"male","category":"Economics"},{"gender":"male","category":"Economics"},{"gender":"male","category":"Chemistry"},{"gender":"female","category":"Chemistry"},{"gender":"male","category":"Physics"},{"gender":"male","category":"Physiology or Medicine"},{"gender":"male","category":"Economics"},{"gender":"male","category":"Chemistry"},{"gender":"male","category":"Physics"},{"gender":"male","category":"Physics"},{"gender":"male","category":"Physiology or Medicine"},{"gender":"male","category":"Physiology or Medicine"},{"gender":"male","category":"Economics"},{"gender":"male","category":"Economics"},{"gender":"male","category":"Chemistry"},{"gender":"male","category":"Chemistry"},{"gender":"male","category":"Physics"},{"gender":"male","category":"Economics"},{"gender":"female","category":"Literature"},{"gender":"female","category":"Chemistry"},{"gender":"female","category":"Physics"},{"gender":"male","category":"Chemistry"},{"gender":"male","category":"Physiology or Medicine"},{"gender":"male","category":"Economics"},{"gender":"male","category":"Economics"},{"gender":"male","category":"Economics"},{"gender":"female","category":"Chemistry"},{"gender":"male","category":"Chemistry"},{"gender":"male","category":"Physics"},{"gender":"male","category":"Literature"},{"gender":"male","category":"Physics"},{"gender":"male","category":"Physics"},{"gender":"male","category":"Literature"},{"gender":"male","category":"Physiology or Medicine"},{"gender":"male","category":"Chemistry"},{"gender":"male","category":"Chemistry"},{"gender":"male","category":"Physics"},{"gender":"male","category":"Physics"},{"gender":"male","category":"Physics"},{"gender":"male","category":"Chemistry"},{"gender":"male","category":"Chemistry"},{"gender":"male","category":"Peace"},{"gender":"male","category":"Physiology or Medicine"},{"gender":"female","category":"Economics"},{"gender":"male","category":"Chemistry"},{"gender":"male","category":"Physics"},{"gender":"male","category":"Peace"},{"gender":"male","category":"Peace"},{"gender":"male","category":"Physics"},{"gender":"male","category":"Physiology or Medicine"},{"gender":"male","category":"Literature"},{"gender":"male","category":"Chemistry"},{"gender":"male","category":"Physiology or Medicine"},{"gender":"male","category":"Physiology or Medicine"},{"gender":"male","category":"Physics"},{"gender":"male","category":"Peace"},{"gender":"male","category":"Chemistry"},{"gender":"male","category":"Physiology or Medicine"},{"gender":"male","category":"Physiology or Medicine"},{"gender":"male","category":"Chemistry"},{"gender":"male","category":"Physiology or Medicine"},{"gender":"male","category":"Physics"},{"gender":"male","category":"Physics"},{"gender":"male","category":"Peace"},{"gender":"male","category":"Physics"},{"gender":"male","category":"Literature"},{"gender":"male","category":"Physiology or Medicine"},{"gender":"male","category":"Chemistry"},{"gender":"male","category":"Chemistry"},{"gender":"male","category":"Physics"},{"gender":"male","category":"Literature"},{"gender":"male","category":"Physics"},{"gender":"male","category":"Physics"},{"gender":"male","category":"Peace"},{"gender":"male","category":"Literature"},{"gender":"male","category":"Physics"},{"gender":"male","category":"Physiology or Medicine"},{"gender":"male","category":"Chemistry"},{"gender":"male","category":"Chemistry"},{"gender":"male","category":"Physiology or Medicine"},{"gender":"male","category":"Physiology or Medicine"},{"gender":"male","category":"Physiology or Medicine"},{"gender":"male","category":"Physiology or Medicine"},{"gender":"male","category":"Economics"},{"gender":"male","category":"Physiology or Medicine"},{"gender":"male","category":"Chemistry"},{"gender":"male","category":"Chemistry"},{"gender":"male","category":"Chemistry"},{"gender":"female","category":"Chemistry"},{"gender":"male","category":"Physiology or Medicine"},{"gender":"male","category":"Peace"},{"gender":"male","category":"Chemistry"},{"gender":"male","category":"Chemistry"},{"gender":"male","category":"Chemistry"},{"gender":"male","category":"Chemistry"},{"gender":"male","category":"Physics"},{"gender":"male","category":"Chemistry"},{"gender":"male","category":"Economics"},{"gender":"male","category":"Physics"},{"gender":"female","category":"Peace"},{"gender":"male","category":"Economics"},{"gender":"male","category":"Physiology or Medicine"},{"gender":"male","category":"Chemistry"},{"gender":"male","category":"Economics"},{"gender":"male","category":"Physics"},{"gender":"male","category":"Chemistry"},{"gender":"male","category":"Physics"},{"gender":"male","category":"Literature"},{"gender":"male","category":"Chemistry"},{"gender":"male","category":"Physiology or Medicine"},{"gender":"male","category":"Literature"},{"gender":"male","category":"Chemistry"},{"gender":"male","category":"Chemistry"},{"gender":"male","category":"Chemistry"},{"gender":"male","category":"Economics"},{"gender":"male","category":"Peace"},{"gender":"male","category":"Literature"},{"gender":"male","category":"Physiology or Medicine"},{"gender":"male","category":"Physiology or Medicine"},{"gender":"male","category":"Physiology or Medicine"},{"gender":"male","category":"Economics"},{"gender":"male","category":"Literature"},{"gender":"male","category":"Economics"},{"gender":"male","category":"Physiology or Medicine"},{"gender":"male","category":"Physiology or Medicine"},{"gender":"male","category":"Physiology or Medicine"},{"gender":"male","category":"Physics"},{"gender":"male","category":"Physiology or Medicine"},{"gender":"male","category":"Physics"},{"gender":"male","category":"Chemistry"},{"gender":"female","category":"Literature"},{"gender":"male","category":"Physiology or Medicine"},{"gender":"male","category":"Physiology or Medicine"},{"gender":"male","category":"Physiology or Medicine"},{"gender":"male","category":"Physiology or Medicine"},{"gender":"male","category":"Literature"},{"gender":"male","category":"Chemistry"},{"gender":"male","category":"Physics"},{"gender":"male","category":"Physiology or Medicine"},{"gender":"male","category":"Physiology or Medicine"},{"gender":"male","category":"Chemistry"},{"gender":"male","category":"Literature"},{"gender":"male","category":"Chemistry"},{"gender":"male","category":"Chemistry"},{"gender":"male","category":"Literature"},{"gender":"male","category":"Physiology or Medicine"},{"gender":"male","category":"Economics"},{"gender":"male","category":"Physics"},{"gender":"male","category":"Physics"},{"gender":"male","category":"Physics"},{"gender":"male","category":"Economics"},{"gender":"male","category":"Peace"},{"gender":"male","category":"Physics"},{"gender":"male","category":"Literature"},{"gender":"male","category":"Chemistry"},{"gender":"male","category":"Physiology or Medicine"},{"gender":"male","category":"Peace"},{"gender":"male","category":"Peace"},{"gender":"male","category":"Peace"},{"gender":"male","category":"Physics"},{"gender":"male","category":"Physiology or Medicine"},{"gender":"male","category":"Literature"},{"gender":"male","category":"Chemistry"},{"gender":"male","category":"Chemistry"},{"gender":"male","category":"Physics"},{"gender":"male","category":"Physics"},{"gender":"male","category":"Chemistry"},{"gender":"male","category":"Chemistry"},{"gender":"male","category":"Physiology or Medicine"},{"gender":"male","category":"Physiology or Medicine"},{"gender":"male","category":"Literature"},{"gender":"male","category":"Physics"},{"gender":"male","category":"Physiology or Medicine"},{"gender":"female","category":"Literature"},{"gender":"male","category":"Peace"},{"gender":"male","category":"Chemistry"},{"gender":"male","category":"Physics"},{"gender":"male","category":"Physics"},{"gender":"male","category":"Physiology or Medicine"},{"gender":"male","category":"Physiology or Medicine"},{"gender":"male","category":"Physiology or Medicine"},{"gender":"male","category":"Physiology or Medicine"},{"gender":"male","category":"Chemistry"},{"gender":"male","category":"Literature"},{"gender":"male","category":"Peace"},{"gender":"male","category":"Chemistry"},{"gender":"male","category":"Chemistry"},{"gender":"male","category":"Physiology or Medicine"},{"gender":"male","category":"Physiology or Medicine"},{"gender":"male","category":"Physics"},{"gender":"male","category":"Physiology or Medicine"},{"gender":"male","category":"Economics"},{"gender":"male","category":"Literature"},{"gender":"male","category":"Literature"},{"gender":"male","category":"Economics"},{"gender":"male","category":"Physiology or Medicine"},{"gender":"male","category":"Physics"},{"gender":"male","category":"Physiology or Medicine"},{"gender":"female","category":"Literature"},{"gender":"male","category":"Peace"},{"gender":"male","category":"Physiology or Medicine"},{"gender":"male","category":"Literature"},{"gender":"male","category":"Physics"},{"gender":"male","category":"Peace"},{"gender":"male","category":"Physiology or Medicine"},{"gender":"male","category":"Physics"},{"gender":"male","category":"Physics"},{"gender":"male","category":"Physiology or Medicine"},{"gender":"male","category":"Physiology or Medicine"},{"gender":"male","category":"Chemistry"},{"gender":"male","category":"Literature"},{"gender":"male","category":"Physiology or Medicine"},{"gender":"female","category":"Peace"},{"gender":"male","category":"Physiology or Medicine"},{"gender":"male","category":"Peace"},{"gender":"male","category":"Literature"},{"gender":"male","category":"Literature"},{"gender":"male","category":"Peace"},{"gender":"female","category":"Literature"},{"gender":"male","category":"Peace"},{"gender":"male","category":"Peace"},{"gender":"male","category":"Literature"},{"gender":"male","category":"Literature"},{"gender":"male","category":"Literature"},{"gender":"male","category":"Physiology or Medicine"},{"gender":"male","category":"Literature"},{"gender":"female","category":"Physics"},{"gender":"male","category":"Peace"},{"gender":"male","category":"Physiology or Medicine"},{"gender":"male","category":"Physiology or Medicine"},{"gender":"male","category":"Literature"},{"gender":"male","category":"Literature"},{"gender":"male","category":"Physics"},{"gender":"male","category":"Physics"},{"gender":"male","category":"Physics"},{"gender":"male","category":"Literature"},{"gender":"male","category":"Physics"},{"gender":"male","category":"Physics"},{"gender":"male","category":"Physics"},{"gender":"male","category":"Chemistry"},{"gender":"male","category":"Literature"},{"gender":"male","category":"Literature"},{"gender":"male","category":"Peace"},{"gender":"female","category":"Peace"},{"gender":"male","category":"Peace"},{"gender":"male","category":"Physics"},{"gender":"male","category":"Physics"},{"gender":"male","category":"Peace"},{"gender":"male","category":"Physics"},{"gender":"male","category":"Economics"},{"gender":"male","category":"Economics"},{"gender":"male","category":"Peace"},{"gender":"male","category":"Literature"},{"gender":"female","category":"Chemistry"},{"gender":"male","category":"Literature"},{"gender":"female","category":"Physics"},{"gender":"male","category":"Literature"},{"gender":"male","category":"Physiology or Medicine"},{"gender":"male","category":"Peace"},{"gender":"male","category":"Peace"},{"gender":"female","category":"Literature"},{"gender":"female","category":"Literature"},{"gender":"male","category":"Peace"},{"gender":"female","category":"Peace"},{"gender":"male","category":"Literature"},{"gender":"female","category":"Peace"},{"gender":"male","category":"Literature"},{"gender":"male","category":"Physics"},{"gender":"male","category":"Peace"},{"gender":"male","category":"Peace"},{"gender":"male","category":"Peace"},{"gender":"female","category":"Literature"},{"gender":"male","category":"Physics"},{"gender":"male","category":"Economics"},{"gender":"male","category":"Chemistry"},{"gender":"male","category":"Chemistry"},{"gender":"female","category":"Literature"},{"gender":"male","category":"Chemistry"},{"gender":"male","category":"Physiology or Medicine"},{"gender":"male","category":"Literature"},{"gender":"male","category":"Literature"},{"gender":"female","category":"Physiology or Medicine"},{"gender":"male","category":"Physiology or Medicine"},{"gender":"male","category":"Economics"},{"gender":"male","category":"Economics"},{"gender":"male","category":"Physics"},{"gender":"male","category":"Physics"},{"gender":"male","category":"Economics"},{"gender":"male","category":"Economics"},{"gender":"female","category":"Peace"},{"gender":"male","category":"Economics"},{"gender":"male","category":"Chemistry"},{"gender":"male","category":"Physics"},{"gender":"male","category":"Physics"},{"gender":"male","category":"Physics"},{"gender":"male","category":"Chemistry"},{"gender":"male","category":"Physiology or Medicine"},{"gender":"male","category":"Physiology or Medicine"},{"gender":"male","category":"Physics"},{"gender":"male","category":"Peace"},{"gender":"male","category":"Physics"},{"gender":"male","category":"Physics"},{"gender":"male","category":"Physics"},{"gender":"male","category":"Chemistry"},{"gender":"male","category":"Physics"},{"gender":"female","category":"Peace"},{"gender":"female","category":"Peace"},{"gender":"female","category":"Peace"},{"gender":"male","category":"Peace"},{"gender":"male","category":"Physics"},{"gender":"male","category":"Literature"},{"gender":"male","category":"Physics"},{"gender":"male","category":"Literature"},{"gender":"male","category":"Peace"},{"gender":"male","category":"Physiology or Medicine"},{"gender":"male","category":"Chemistry"},{"gender":"male","category":"Chemistry"},{"gender":"male","category":"Physics"},{"gender":"male","category":"Physics"},{"gender":"male","category":"Chemistry"},{"gender":"male","category":"Physics"},{"gender":"male","category":"Chemistry"},{"gender":"male","category":"Physiology or Medicine"},{"gender":"male","category":"Physiology or Medicine"},{"gender":"male","category":"Physics"},{"gender":"male","category":"Physiology or Medicine"},{"gender":"male","category":"Physics"},{"gender":"male","category":"Physics"},{"gender":"male","category":"Chemistry"},{"gender":"male","category":"Chemistry"},{"gender":"male","category":"Literature"},{"gender":"male","category":"Physiology or Medicine"},{"gender":"male","category":"Chemistry"},{"gender":"female","category":"Literature"},{"gender":"male","category":"Physics"},{"gender":"male","category":"Peace"},{"gender":"male","category":"Physiology or Medicine"},{"gender":"male","category":"Literature"},{"gender":"male","category":"Chemistry"},{"gender":"male","category":"Literature"},{"gender":"male","category":"Physiology or Medicine"},{"gender":"male","category":"Physics"},{"gender":"male","category":"Literature"},{"gender":"male","category":"Physics"},{"gender":"male","category":"Literature"},{"gender":"male","category":"Peace"},{"gender":"male","category":"Literature"},{"gender":"male","category":"Physics"},{"gender":"male","category":"Peace"},{"gender":"male","category":"Peace"},{"gender":"male","category":"Literature"},{"gender":"male","category":"Chemistry"},{"gender":"male","category":"Chemistry"},{"gender":"female","category":"Chemistry"},{"gender":"male","category":"Economics"},{"gender":"male","category":"Chemistry"},{"gender":"male","category":"Chemistry"},{"gender":"female","category":"Peace"},{"gender":"male","category":"Peace"},{"gender":"male","category":"Literature"},{"gender":"male","category":"Physics"},{"gender":"male","category":"Literature"},{"gender":"male","category":"Economics"},{"gender":"male","category":"Chemistry"},{"gender":"female","category":"Peace"},{"gender":"female","category":"Peace"},{"gender":"female","category":"Peace"},{"gender":"male","category":"Physiology or Medicine"},{"gender":"male","category":"Peace"},{"gender":"male","category":"Physics"},{"gender":"male","category":"Literature"},{"gender":"male","category":"Peace"},{"gender":"male","category":"Literature"},{"gender":"male","category":"Peace"},{"gender":"male","category":"Economics"},{"gender":"male","category":"Chemistry"},{"gender":"male","category":"Physiology or Medicine"},{"gender":"male","category":"Physics"},{"gender":"male","category":"Physics"},{"gender":"male","category":"Physiology or Medicine"},{"gender":"male","category":"Literature"},{"gender":"female","category":"Peace"},{"gender":"male","category":"Literature"},{"gender":"male","category":"Chemistry"},{"gender":"male","category":"Peace"},{"gender":"male","category":"Literature"},{"gender":"male","category":"Literature"},{"gender":"female","category":"Peace"},{"gender":"male","category":"Literature"},{"gender":"male","category":"Physics"},{"gender":"male","category":"Chemistry"},{"gender":"male","category":"Chemistry"},{"gender":"male","category":"Literature"},{"gender":"male","category":"Physiology or Medicine"},{"gender":"male","category":"Physics"},{"gender":"female","category":"Physiology or Medicine"},{"gender":"male","category":"Physics"},{"gender":"male","category":"Literature"},{"gender":"male","category":"Physics"},{"gender":"male","category":"Chemistry"},{"gender":"male","category":"Physics"},{"gender":"male","category":"Physiology or Medicine"},{"gender":"male","category":"Physics"},{"gender":"male","category":"Physics"},{"gender":"male","category":"Chemistry"},{"gender":"male","category":"Physics"},{"gender":"male","category":"Chemistry"},{"gender":"male","category":"Physics"},{"gender":"male","category":"Chemistry"},{"gender":"male","category":"Physiology or Medicine"},{"gender":"male","category":"Literature"},{"gender":"male","category":"Physics"},{"gender":"male","category":"Chemistry"},{"gender":"male","category":"Literature"},{"gender":"male","category":"Physiology or Medicine"},{"gender":"male","category":"Chemistry"},{"gender":"male","category":"Physiology or Medicine"},{"gender":"male","category":"Peace"},{"gender":"male","category":"Physiology or Medicine"},{"gender":"male","category":"Physics"},{"gender":"male","category":"Physiology or Medicine"},{"gender":"male","category":"Chemistry"},{"gender":"male","category":"Chemistry"},{"gender":"male","category":"Chemistry"},{"gender":"male","category":"Chemistry"},{"gender":"male","category":"Chemistry"},{"gender":"male","category":"Chemistry"},{"gender":"male","category":"Physiology or Medicine"},{"gender":"male","category":"Chemistry"},{"gender":"male","category":"Chemistry"},{"gender":"male","category":"Literature"},{"gender":"male","category":"Chemistry"},{"gender":"male","category":"Peace"},{"gender":"male","category":"Chemistry"},{"gender":"male","category":"Peace"},{"gender":"male","category":"Physiology or Medicine"},{"gender":"male","category":"Chemistry"},{"gender":"male","category":"Chemistry"},{"gender":"male","category":"Physics"},{"gender":"male","category":"Physics"},{"gender":"male","category":"Physiology or Medicine"},{"gender":"male","category":"Physics"},{"gender":"male","category":"Chemistry"},{"gender":"male","category":"Peace"},{"gender":"male","category":"Chemistry"},{"gender":"male","category":"Chemistry"},{"gender":"male","category":"Physics"},{"gender":"male","category":"Chemistry"},{"gender":"male","category":"Chemistry"},{"gender":"male","category":"Physics"},{"gender":"male","category":"Chemistry"},{"gender":"male","category":"Physics"},{"gender":"male","category":"Physics"},{"gender":"male","category":"Physics"},{"gender":"male","category":"Physiology or Medicine"},{"gender":"male","category":"Literature"},{"gender":"male","category":"Physics"},{"gender":"male","category":"Chemistry"},{"gender":"female","category":"Physiology or Medicine"},{"gender":"male","category":"Economics"},{"gender":"male","category":"Physiology or Medicine"},{"gender":"male","category":"Physiology or Medicine"},{"gender":"female","category":"Literature"},{"gender":"male","category":"Physiology or Medicine"},{"gender":"male","category":"Chemistry"},{"gender":"male","category":"Physics"},{"gender":"male","category":"Chemistry"},{"gender":"male","category":"Physics"},{"gender":"male","category":"Physics"},{"gender":"male","category":"Physics"},{"gender":"male","category":"Literature"},{"gender":"male","category":"Physiology or Medicine"},{"gender":"male","category":"Chemistry"},{"gender":"male","category":"Physics"},{"gender":"male","category":"Peace"},{"gender":"male","category":"Literature"},{"gender":"male","category":"Chemistry"},{"gender":"male","category":"Chemistry"},{"gender":"male","category":"Peace"},{"gender":"male","category":"Physics"},{"gender":"male","category":"Physiology or Medicine"},{"gender":"male","category":"Peace"},{"gender":"male","category":"Chemistry"},{"gender":"male","category":"Literature"},{"gender":"male","category":"Physics"},{"gender":"male","category":"Physics"},{"gender":"male","category":"Physics"},{"gender":"male","category":"Literature"},{"gender":"male","category":"Physiology or Medicine"},{"gender":"male","category":"Physiology or Medicine"},{"gender":"male","category":"Chemistry"},{"gender":"female","category":"Chemistry"},{"gender":"male","category":"Literature"},{"gender":"male","category":"Physics"},{"gender":"male","category":"Physiology or Medicine"},{"gender":"male","category":"Literature"},{"gender":"male","category":"Peace"},{"gender":"male","category":"Peace"},{"gender":"male","category":"Physics"},{"gender":"male","category":"Literature"},{"gender":"male","category":"Peace"},{"gender":"male","category":"Literature"},{"gender":"male","category":"Literature"},{"gender":"male","category":"Physiology or Medicine"},{"gender":"male","category":"Physiology or Medicine"},{"gender":"male","category":"Physiology or Medicine"},{"gender":"male","category":"Literature"},{"gender":"male","category":"Physics"},{"gender":"male","category":"Peace"},{"gender":"male","category":"Physics"},{"gender":"male","category":"Literature"},{"gender":"male","category":"Literature"},{"gender":"male","category":"Physiology or Medicine"},{"gender":"male","category":"Literature"},{"gender":"male","category":"Peace"},{"gender":"male","category":"Peace"},{"gender":"male","category":"Economics"},{"gender":"male","category":"Physiology or Medicine"},{"gender":"male","category":"Literature"},{"gender":"male","category":"Physiology or Medicine"},{"gender":"female","category":"Physiology or Medicine"},{"gender":"male","category":"Physics"},{"gender":"male","category":"Chemistry"},{"gender":"male","category":"Literature"},{"gender":"male","category":"Literature"},{"gender":"male","category":"Physics"},{"gender":"male","category":"Physiology or Medicine"},{"gender":"male","category":"Physics"},{"gender":"male","category":"Physics"},{"gender":"male","category":"Physics"},{"gender":"male","category":"Economics"},{"gender":"male","category":"Chemistry"},{"gender":"male","category":"Literature"},{"gender":"male","category":"Chemistry"},{"gender":"male","category":"Economics"},{"gender":"male","category":"Chemistry"},{"gender":"female","category":"Literature"},{"gender":"male","category":"Economics"},{"gender":"male","category":"Peace"},{"gender":"male","category":"Literature"},{"gender":"male","category":"Peace"},{"gender":"male","category":"Peace"},{"gender":"male","category":"Physics"},{"gender":"female","category":"Chemistry"},{"gender":"female","category":"Economics"},{"gender":"male","category":"Physics"},{"gender":"male","category":"Physiology or Medicine"},{"gender":"male","category":"Peace"},{"gender":"male","category":"Peace"},{"gender":"male","category":"Peace"},{"gender":"male","category":"Chemistry"},{"gender":"male","category":"Physiology or Medicine"},{"gender":"male","category":"Physics"},{"gender":"male","category":"Physiology or Medicine"},{"gender":"male","category":"Physics"},{"gender":"male","category":"Literature"},{"gender":"male","category":"Chemistry"},{"gender":"male","category":"Chemistry"},{"gender":"male","category":"Chemistry"},{"gender":"male","category":"Literature"},{"gender":"male","category":"Physiology or Medicine"},{"gender":"male","category":"Physiology or Medicine"},{"gender":"male","category":"Physics"},{"gender":"male","category":"Literature"},{"gender":"male","category":"Literature"},{"gender":"male","category":"Peace"},{"gender":"male","category":"Literature"},{"gender":"male","category":"Peace"},{"gender":"male","category":"Peace"},{"gender":"male","category":"Literature"},{"gender":"male","category":"Peace"},{"gender":"male","category":"Peace"},{"gender":"male","category":"Physiology or Medicine"},{"gender":"male","category":"Literature"},{"gender":"female","category":"Literature"},{"gender":"female","category":"Physiology or Medicine"},{"gender":"male","category":"Physics"},{"gender":"male","category":"Chemistry"},{"gender":"male","category":"Chemistry"},{"gender":"male","category":"Peace"},{"gender":"male","category":"Physiology or Medicine"},{"gender":"male","category":"Physics"},{"gender":"female","category":"Physics"},{"gender":"male","category":"Physics"},{"gender":"female","category":"Literature"},{"gender":"male","category":"Physiology or Medicine"},{"gender":"male","category":"Peace"},{"gender":"male","category":"Physiology or Medicine"},{"gender":"male","category":"Physiology or Medicine"},{"gender":"male","category":"Peace"},{"gender":"male","category":"Literature"},{"gender":"male","category":"Peace"},{"gender":"male","category":"Literature"},{"gender":"male","category":"Physiology or Medicine"},{"gender":"male","category":"Physiology or Medicine"},{"gender":"male","category":"Economics"},{"gender":"male","category":"Physics"},{"gender":"male","category":"Chemistry"},{"gender":"male","category":"Physics"},{"gender":"male","category":"Chemistry"},{"gender":"male","category":"Physiology or Medicine"},{"gender":"male","category":"Physiology or Medicine"},{"gender":"male","category":"Physiology or Medicine"},{"gender":"male","category":"Physics"},{"gender":"male","category":"Physics"},{"gender":"male","category":"Literature"},{"gender":"female","category":"Literature"},{"gender":"male","category":"Physics"},{"gender":"male","category":"Physiology or Medicine"},{"gender":"male","category":"Physiology or Medicine"},{"gender":"male","category":"Physiology or Medicine"},{"gender":"male","category":"Physiology or Medicine"},{"gender":"male","category":"Literature"},{"gender":"male","category":"Physics"},{"gender":"male","category":"Peace"},{"gender":"male","category":"Chemistry"},{"gender":"male","category":"Physiology or Medicine"},{"gender":"male","category":"Peace"},{"gender":"male","category":"Physiology or Medicine"}]