[{"link":"https:\/\/en.wikipedia.org\/wiki\/Bj%C3%B8rnstjerne_Bj%C3%B8rnson","year":1903,"category":"Literature","country":"Norway","text":"Bj\u00f8rnstjerne Bj\u00f8rnson , Literature, 1903","wikidata_code":"Q46405","date_of_birth":"1832-12-08T00:00:00.000","date_of_death":"1910-04-26T00:00:00.000","place_of_birth":"Kvikne","place_of_death":"Paris","gender":"male","born_in":null,"award_age":71},{"link":"https:\/\/en.wikipedia.org\/wiki\/Knut_Hamsun","year":1920,"category":"Literature","country":"Norway","text":"Knut Hamsun , Literature, 1920","wikidata_code":"Q40826","date_of_birth":"1859-08-04T00:00:00.000","date_of_death":"1952-02-19T00:00:00.000","place_of_birth":"V\u00e5g\u00e5","place_of_death":"Grimstad","gender":"male","born_in":null,"award_age":61},{"link":"https:\/\/en.wikipedia.org\/wiki\/Fridtjof_Nansen","year":1922,"category":"Peace","country":"Norway","text":"Fridtjof Nansen , Peace, 1922","wikidata_code":"Q72292","date_of_birth":"1861-10-10T00:00:00.000","date_of_death":"1930-05-13T00:00:00.000","place_of_birth":"Vestre Aker","place_of_death":"Polh\u00f8gda","gender":"male","born_in":null,"award_age":61},{"link":"https:\/\/en.wikipedia.org\/wiki\/Christian_Lous_Lange","year":1921,"category":"Peace","country":"Norway","text":"Christian Lous Lange , Peace, 1921","wikidata_code":"Q206446","date_of_birth":"1869-09-17T00:00:00.000","date_of_death":"1938-12-11T00:00:00.000","place_of_birth":"Stavanger Municipality","place_of_death":"Oslo","gender":"male","born_in":null,"award_age":52},{"link":"https:\/\/en.wikipedia.org\/wiki\/Ivar_Giaever","year":1973,"category":"Physics","country":"Norway","text":"Ivar Giaever , Physics, 1973","wikidata_code":"Q192688","date_of_birth":"1929-04-05T00:00:00.000","date_of_death":null,"place_of_birth":"Bergen","place_of_death":null,"gender":"male","born_in":null,"award_age":44},{"link":"https:\/\/en.wikipedia.org\/wiki\/Ragnar_Frisch","year":1969,"category":"Economics","country":"Norway","text":"Ragnar Frisch , Economics, 1969","wikidata_code":"Q187988","date_of_birth":"1895-03-03T00:00:00.000","date_of_death":"1973-01-31T00:00:00.000","place_of_birth":"Christiania","place_of_death":"Oslo","gender":"male","born_in":null,"award_age":74},{"link":"https:\/\/en.wikipedia.org\/wiki\/Odd_Hassel","year":1969,"category":"Chemistry","country":"Norway","text":"Odd Hassel , Chemistry, 1969","wikidata_code":"Q157212","date_of_birth":"1897-05-17T00:00:00.000","date_of_death":"1981-05-11T00:00:00.000","place_of_birth":"Christiania","place_of_death":"Oslo","gender":"male","born_in":null,"award_age":72},{"link":"https:\/\/en.wikipedia.org\/wiki\/Lars_Onsager","year":1968,"category":"Chemistry","country":"Norway","text":"Lars Onsager , Chemistry, 1968","wikidata_code":"Q107405","date_of_birth":"1903-11-27T00:00:00.000","date_of_death":"1976-10-05T00:00:00.000","place_of_birth":"Christiania","place_of_death":"Coral Gables","gender":"male","born_in":null,"award_age":65},{"link":"https:\/\/en.wikipedia.org\/wiki\/Sigrid_Undset","year":1928,"category":"Literature","country":"Norway","text":"Sigrid Undset , Literature, 1928","wikidata_code":"Q80889","date_of_birth":"1882-05-20T00:00:00.000","date_of_death":"1949-06-10T00:00:00.000","place_of_birth":"Kalundborg","place_of_death":"Lillehammer Municipality","gender":"female","born_in":null,"award_age":46},{"link":"https:\/\/en.wikipedia.org\/wiki\/Jon_Fosse","year":2023,"category":"Literature","country":"Norway","text":"Jon Fosse , Literature, 2023","wikidata_code":"Q443868","date_of_birth":"1959-09-29T00:00:00.000","date_of_death":null,"place_of_birth":"Haugesund Municipality","place_of_death":null,"gender":"male","born_in":null,"award_age":64},{"link":"https:\/\/en.wikipedia.org\/wiki\/May-Britt_Moser","year":2014,"category":"Physiology or Medicine","country":"Norway","text":"May-Britt Moser , Physiology or Medicine, 2014","wikidata_code":"Q6796222","date_of_birth":"1963-01-04T00:00:00.000","date_of_death":null,"place_of_birth":"Fosnav\u00e5g","place_of_death":null,"gender":"female","born_in":null,"award_age":51},{"link":"https:\/\/en.wikipedia.org\/wiki\/Edvard_Moser","year":2014,"category":"Physiology or Medicine","country":"Norway","text":"Edvard Moser , Physiology or Medicine, 2014","wikidata_code":"Q5341373","date_of_birth":"1962-04-27T00:00:00.000","date_of_death":null,"place_of_birth":"\u00c5lesund Municipality","place_of_death":null,"gender":"male","born_in":null,"award_age":52},{"link":"https:\/\/en.wikipedia.org\/wiki\/Finn_E._Kydland","year":2004,"category":"Economics","country":"Norway","text":"Finn E. Kydland , Economics, 2004","wikidata_code":"Q211097","date_of_birth":"1943-12-01T00:00:00.000","date_of_death":null,"place_of_birth":"\u00c5lg\u00e5rd","place_of_death":null,"gender":"male","born_in":null,"award_age":61},{"link":"https:\/\/en.wikipedia.org\/wiki\/Trygve_Haavelmo","year":1989,"category":"Economics","country":"Norway","text":"Trygve Haavelmo , Economics, 1989","wikidata_code":"Q208124","date_of_birth":"1911-12-13T00:00:00.000","date_of_death":"1999-07-28T00:00:00.000","place_of_birth":"Skedsmo Municipality","place_of_death":"B\u00e6rum Municipality","gender":"male","born_in":null,"award_age":78}]